metanode/__init__.py
metanode/graphene_auth.py
metanode/graphene_constants.py
metanode/graphene_metanode_client.py
metanode/graphene_metanode_server.py
metanode/graphene_rpc.py
metanode/graphene_signing.py
metanode/graphene_sql.py
metanode/graphene_utils.py
metanode/unit_test_dbux.py
metanode/unit_test_delint.py
metanode/unit_test_private.py
metanode/unit_test_public.py
metanode-1.0.8.dist-info/LICENSE.txt
metanode-1.0.8.dist-info/METADATA
metanode-1.0.8.dist-info/WHEEL
metanode-1.0.8.dist-info/top_level.txt
metanode-1.0.8.dist-info/RECORD
