Metadata-Version: 2.1
Name: metanode
Version: 1.0.8
Summary: metanode = GrapheneTrustlessClient()
Home-page: https://github.com/litepresence/Graphene-Metanode
Author: litepresence
Author-email: finitestate@tutamail.com
License: MIT
Classifier: Programming Language :: Python
Classifier: Programming Language :: Python :: 3
Classifier: Programming Language :: Python :: 3.8
Classifier: Programming Language :: Python :: 3.9
Classifier: Programming Language :: Python :: 3.10
License-File: LICENSE.txt
Requires-Dist: websocket-client>=1.2.3
Requires-Dist: requests
Requires-Dist: secp256k1<=0.13.2
Requires-Dist: ecdsa==0.17.0
Requires-Dist: psutil
